{
  "type": "forge:conditional",
  "recipes": [
    {
      "conditions": [
        {
          "feature": "create_connected:linked_transmitter",
          "invert": false,
          "type": "create_connected:feature_enabled"
        },
        {
          "feature": "create:redstone_link",
          "invert": false,
          "type": "create_connected:feature_enabled"
        }
      ],
      "recipe": {
        "type": "minecraft:crafting_shapeless",
        "ingredients": [
          {
            "item": "create_connected:linked_transmitter"
          }
        ],
        "result": {
          "item": "create:redstone_link"
        }
      }
    }
  ]
}